njdoe/__init__.py
njdoe/certification.py
njdoe/criminal_history.py
njdoe-0.1.1.dist-info/WHEEL
njdoe-0.1.1.dist-info/METADATA
njdoe-0.1.1.dist-info/RECORD
