Metadata-Version: 2.1
Name: njdoe
Version: 0.1.1
License: MIT
Author-email: Charlie Bini <5003326+cbini@users.noreply.github.com>
Requires-Python: >=3.9
Requires-Dist: beautifulsoup4>=4.10.0
Requires-Dist: requests>=2.27.1
